[
	{
		"planets": [
			{
				"scale": 1,
				"links": [1],
				"x": 4,
				"y": 3
			},
			{
				"scale": 1.1,
				"links": [0, 2],
				"x": 6,
				"y": 5
			},
			{
				"scale": 1,
				"links": [1],
				"x": 11,
				"y": 6
			}
		]
	},
	{
		"planets": [
			{
				"scale": 1.1,
				"links": [1, 2],
				"x": 4,
				"y": 4
			},
			{
				"scale": 1,
				"links": [0, 2, 3],
				"x": 8,
				"y": 3
			},
			{
				"scale": 1,
				"links": [0, 1],
				"x": 7,
				"y": 7
			},
			{
				"scale": 0.7,
				"links": [1],
				"x": 12,
				"y": 4
			}
		]
	},
	{
		"planets": [
			{
				"scale": 0.8,
				"links": [1],
				"x": 2,
				"y": 4
			},
			{
				"scale": 1,
				"links": [0, 2, 3],
				"x": 7,
				"y": 3
			},
			{
				"scale": 1,
				"links": [1, 4],
				"x": 6,
				"y": 8
			},
			{
				"scale": 0.7,
				"links": [1, 4],
				"x": 12,
				"y": 3
			},
			{
				"scale": 0.9,
				"links": [2, 3],
				"x": 12,
				"y": 7
			}
		]
	},
	{
		"planets": [
			{
				"scale": 1,
				"links": [1],
				"x": 2,
				"y": 3
			},
			{
				"scale": 1,
				"links": [0, 2],
				"x": 6,
				"y": 3
			},
			{
				"scale": 0.8,
				"links": [1, 3],
				"x": 9,
				"y": 7
			},
			{
				"scale": 1,
				"links": [2],
				"x": 13,
				"y": 4
			}
		]
	},
	{
		"planets": [
			{
				"scale": 1,
				"links": [1],
				"x": 2,
				"y": 2
			},
			{
				"scale": 1,
				"links": [0, 2, 4],
				"x": 3,
				"y": 7
			},
			{
				"scale": 0.7,
				"links": [1, 3],
				"x": 7,
				"y": 4
			},
			{
				"scale": 0.9,
				"links": [2, 4],
				"x": 13,
				"y": 3
			},
			{
				"scale": 1,
				"links": [1, 3],
				"x": 10,
				"y": 7
			}
		]
	},
	{
		"planets": [
			{
				"scale": 1,
				"links": [2],
				"x": 3,
				"y": 3
			},
			{
				"scale": 1.1,
				"links": [2],
				"x": 5,
				"y": 8
			},
			{
				"scale": 0.7,
				"links": [0, 1, 3, 4],
				"x": 8,
				"y": 4
			},
			{
				"scale": 0.7,
				"links": [2],
				"x": 14,
				"y": 2
			},
			{
				"scale": 1,
				"links": [2],
				"x": 12,
				"y": 6
			}
		]
	}
]
